django_json_api/__init__.py
django_json_api/base.py
django_json_api/client.py
django_json_api/django.py
django_json_api/fields.py
django_json_api/manager.py
django_json_api/models.py
django_json_api/rest_framework.py
django_json_api/version.py
django_json_api/resources/VERSION
tests/__init__.py
tests/apps.py
tests/models.py
tests/settings.py
tests/test_client.py
tests/test_django.py
tests/test_fields.py
tests/test_manager.py
tests/test_models.py
tests/test_rest_framework.py
tests/test_version.py
tests/utils.py
tests/migrations/0001_initial.py
tests/migrations/__init__.py
django_json_api-1.2.1.dist-info/LICENSE
django_json_api-1.2.1.dist-info/METADATA
django_json_api-1.2.1.dist-info/WHEEL
django_json_api-1.2.1.dist-info/top_level.txt
django_json_api-1.2.1.dist-info/RECORD
