Metadata-Version: 2.1
Name: django-json-api
Version: 1.2.1
Summary: JSON API specification for Django services
Home-page: https://github.com/share-work/django-json-api
Author: Sharework
Author-email: root@sharework.co
Classifier: Programming Language :: Python :: 3.8
Classifier: License :: OSI Approved :: MIT License
Classifier: Operating System :: OS Independent
Requires-Python: >=3.8
License-File: LICENSE
Requires-Dist: djangorestframework-jsonapi (>=6.0.0)
Requires-Dist: djangorestframework (>=3.14.0)
Requires-Dist: python-dateutil (>=2.8.2)
Provides-Extra: all
Requires-Dist: black (==22.3.0) ; extra == 'all'
Requires-Dist: coverage (==5.4) ; extra == 'all'
Requires-Dist: django-coverage-plugin (==1.8.0) ; extra == 'all'
Requires-Dist: flake8 (==3.8.4) ; extra == 'all'
Requires-Dist: isort (==5.7.0) ; extra == 'all'
Requires-Dist: pre-commit (==2.10.0) ; extra == 'all'
Requires-Dist: pytest-cov (==2.11.1) ; extra == 'all'
Requires-Dist: pytest-django (==4.5.2) ; extra == 'all'
Requires-Dist: pytest (==7.2.1) ; extra == 'all'
Requires-Dist: requests-mock (==1.8.0) ; extra == 'all'
Requires-Dist: testfixtures (==6.17.1) ; extra == 'all'
Provides-Extra: dev
Requires-Dist: black (==22.3.0) ; extra == 'dev'
Requires-Dist: coverage (==5.4) ; extra == 'dev'
Requires-Dist: django-coverage-plugin (==1.8.0) ; extra == 'dev'
Requires-Dist: flake8 (==3.8.4) ; extra == 'dev'
Requires-Dist: isort (==5.7.0) ; extra == 'dev'
Requires-Dist: pre-commit (==2.10.0) ; extra == 'dev'
Requires-Dist: pytest-cov (==2.11.1) ; extra == 'dev'
Requires-Dist: pytest-django (==4.5.2) ; extra == 'dev'
Requires-Dist: pytest (==7.2.1) ; extra == 'dev'
Requires-Dist: requests-mock (==1.8.0) ; extra == 'dev'
Requires-Dist: testfixtures (==6.17.1) ; extra == 'dev'
